unv/__init__.py
unv/web/__init__.py
unv/web/app.py
unv/web/bin.py
unv/web/decorators.py
unv/web/helpers.py
unv/web/settings.py
unv/web/deploy/__init__.py
unv/web/deploy/app.service
unv/web/deploy/ipv4.rules
unv/web/deploy/nginx.conf
unv.web-0.4.6.dist-info/LICENSE
unv.web-0.4.6.dist-info/METADATA
unv.web-0.4.6.dist-info/WHEEL
unv.web-0.4.6.dist-info/entry_points.txt
unv.web-0.4.6.dist-info/top_level.txt
unv.web-0.4.6.dist-info/zip-safe
unv.web-0.4.6.dist-info/RECORD
