Metadata-Version: 2.1
Name: unv.web
Version: 0.4.6
Summary: Web application helpers for unv based on aiohttp
Home-page: http://github.com/c137digital/unv_web
Author: Morty Space
Author-email: morty.space@gmail.com
License: MIT
Platform: UNKNOWN
Classifier: Development Status :: 4 - Beta
Classifier: Intended Audience :: Developers
Classifier: License :: OSI Approved :: MIT License
Classifier: Operating System :: POSIX
Classifier: Operating System :: MacOS :: MacOS X
Classifier: Programming Language :: Python
Classifier: Programming Language :: Python :: 3
Classifier: Programming Language :: Python :: 3.7
Classifier: Programming Language :: Python :: Implementation :: CPython
Classifier: Topic :: Software Development :: Libraries :: Application Frameworks
Classifier: Topic :: Software Development :: Libraries :: Python Modules
Requires-Dist: unv.app
Requires-Dist: unv.deploy
Requires-Dist: aiohttp
Requires-Dist: uvloop
Requires-Dist: ujson
Requires-Dist: jinja2
Requires-Dist: aioredis
Provides-Extra: dev
Requires-Dist: pylint ; extra == 'dev'
Requires-Dist: pycodestyle ; extra == 'dev'
Requires-Dist: pytest ; extra == 'dev'
Requires-Dist: pytest-cov ; extra == 'dev'
Requires-Dist: pytest-env ; extra == 'dev'
Requires-Dist: pytest-pythonpath ; extra == 'dev'
Requires-Dist: pytest-aiohttp ; extra == 'dev'
Requires-Dist: autopep8 ; extra == 'dev'
Requires-Dist: sphinx ; extra == 'dev'
Requires-Dist: setuptools ; extra == 'dev'
Requires-Dist: wheel ; extra == 'dev'
Requires-Dist: twine ; extra == 'dev'
